py_local/__init__.py
py_local/config.py
py_local/main.py
py_local-0.5.3.dist-info/licenses/LICENSE
py_local-0.5.3.dist-info/METADATA
py_local-0.5.3.dist-info/WHEEL
py_local-0.5.3.dist-info/top_level.txt
py_local-0.5.3.dist-info/RECORD
