Metadata-Version: 2.4
Name: py-local
Version: 0.5.3
Summary: Local Network Module for Python
Home-page: https://github.com/codelao/py-local
Author: Lao
License: MIT
License-File: LICENSE
Requires-Dist: fake-useragent>=1.3.0
Requires-Dist: colorama>=0.4.6
Dynamic: author
Dynamic: description
Dynamic: description-content-type
Dynamic: home-page
Dynamic: license
Dynamic: license-file
Dynamic: requires-dist
Dynamic: summary
